{
  "type": "minecraft:crafting_shaped",
  "pattern": [
    "012",
    "345",
    " 7 "
  ],
  "key": {
    "0": {
      "item": "tmim:dark_energon_shard"
    },
    "1": {
      "item": "minecraft:cobblestone"
    },
    "2": {
      "item": "minecraft:cobblestone"
    },
    "3": {
      "item": "tmim:dark_energon_shard"
    },
    "4": {
      "item": "minecraft:cobblestone"
    },
    "5": {
      "item": "minecraft:cobblestone"
    },
    "7": {
      "item": "tmim:iron_rod"
    }
  },
  "result": {
    "item": "tmim:block_replacer_v_6",
    "count": 1
  }
}