{
  "type": "minecraft:crafting_shaped",
  "pattern": [
    "012",
    "345",
    " 7 "
  ],
  "key": {
    "0": {
      "item": "tmim:iron_gear"
    },
    "1": {
      "item": "tmim:copper_plating"
    },
    "2": {
      "item": "tmim:iron_gear"
    },
    "3": {
      "item": "tmim:copper_plating"
    },
    "4": {
      "item": "tmim:storage_controller"
    },
    "5": {
      "item": "tmim:copper_plating"
    },
    "7": {
      "item": "tmim:copper_plating"
    }
  },
  "result": {
    "item": "tmim:copper_container",
    "count": 1
  }
}