{
  "_fv": 24,
  "_type": "recipe",
  "definition": {
    "recipeType": "Crafting",
    "xpReward": 0.0,
    "cookingTime": 200,
    "recipeRetstackSize": 1,
    "group": "",
    "recipeShapeless": false,
    "recipeSlots": [
      {
        "value": "Blocks.GLASS"
      },
      {
        "value": "CUSTOM:TitaniumIngot"
      },
      {
        "value": "Blocks.GLASS"
      },
      {
        "value": "CUSTOM:TitaniumIngot"
      },
      {
        "value": ""
      },
      {
        "value": "CUSTOM:TitaniumIngot"
      },
      {
        "value": "Blocks.GLASS"
      },
      {
        "value": "CUSTOM:TitaniumIngot"
      },
      {
        "value": "Blocks.GLASS"
      }
    ],
    "recipeReturnStack": {
      "value": "CUSTOM:FluidContainer"
    },
    "name": "craft_fluid_container",
    "namespace": "mod"
  }
}