{
  "_fv": 24,
  "_type": "recipe",
  "definition": {
    "recipeType": "Crafting",
    "xpReward": 0.0,
    "cookingTime": 200,
    "recipeRetstackSize": 1,
    "group": "",
    "recipeShapeless": false,
    "recipeSlots": [
      {
        "value": "CUSTOM:StoneGear"
      },
      {
        "value": "CUSTOM:Aluminumplating"
      },
      {
        "value": "CUSTOM:StoneGear"
      },
      {
        "value": "CUSTOM:Aluminumplating"
      },
      {
        "value": "CUSTOM:StorageController"
      },
      {
        "value": "CUSTOM:Aluminumplating"
      },
      {
        "value": ""
      },
      {
        "value": "CUSTOM:Aluminumplating"
      },
      {
        "value": ""
      }
    ],
    "recipeReturnStack": {
      "value": "CUSTOM:AluminiumContainer"
    },
    "name": "craftaluminumcontainer",
    "namespace": "mod"
  }
}